pygesture/__init__.py
pygesture/handtrack.py
pygesture/handtrack_test/__init__.py
pygesture/handtrack_test/function/__init__.py
pygesture/handtrack_test/function/heart.py
pygesture/handtrack_test/function/loveu.py
pygesture/handtrack_test/function/number.py
pygesture/handtrack_test/function/ok.py
pygesture/handtrack_test/function/peace.py
pygesture/handtrack_test/function/power.py
pygesture/handtrack_test/function/thumb.py
pygesture-1.0.7.dist-info/LICENSE
pygesture-1.0.7.dist-info/METADATA
pygesture-1.0.7.dist-info/WHEEL
pygesture-1.0.7.dist-info/top_level.txt
pygesture-1.0.7.dist-info/RECORD
