Metadata-Version: 2.1
Name: pygesture
Version: 1.0.7
Summary: Pre-built OpenCV-Python/Mediapipe modules that easy to use and understand.
Home-page: https://github.com/GoodDay360/pygesture
Author: GoodDay360
Author-email: istartgame31@gmail.com
License: MIT
Keywords: pygesture,library,module,gesture_recognition
Platform: UNKNOWN
Classifier: Development Status :: 5 - Production/Stable
Classifier: Intended Audience :: Information Technology
Classifier: Operating System :: Unix
Classifier: Operating System :: MacOS :: MacOS X
Classifier: Operating System :: Microsoft :: Windows
Classifier: License :: OSI Approved :: MIT License
Classifier: Programming Language :: Python :: 3
License-File: LICENSE
Requires-Dist: protobuf (~=3.20.0)
Requires-Dist: numpy
Requires-Dist: Pillow
Requires-Dist: mediapipe
Requires-Dist: opencv-python
